commons/__init__.py
commons/config.py
configuration/__init__.py
configuration/profile_config.py
dnspod/__init__.py
dnspod/recordsetclient.py
recordset-0.1.3.data/scripts/rset
utils/__init__.py
utils/logger.py
recordset-0.1.3.dist-info/LICENSE
recordset-0.1.3.dist-info/METADATA
recordset-0.1.3.dist-info/WHEEL
recordset-0.1.3.dist-info/top_level.txt
recordset-0.1.3.dist-info/RECORD
