Metadata-Version: 2.1
Name: recordset
Version: 0.1.3
Summary: record operator in Dnspod
Home-page: https://github.com/
Author: xoto
Author-email: xxx.tao.c@gmail.com
Classifier: Programming Language :: Python :: 3
Classifier: License :: OSI Approved :: MIT License
Classifier: Operating System :: OS Independent
License-File: LICENSE
